[
{"id"   : 1 , "name": "~`"       , "class": "desc"                       , "text" : "exit"     , "visible" : true , "emoji" : "⏹️"  },  
{"id"   : 2 , "name": "!1"       , "class": "desc "                      , "text" : "stepOver"     , "visible" : true , "emoji" : "⬇️"  },
{"id"   : 3 , "name": "@2"       , "class": "desc "                      , "text" : "stepInto"     , "visible" : true , "emoji" : "↘️"   },
{"id"   : 4 , "name": "#3"       , "class": "desc "                      , "text" : "resume"     , "visible" : true , "emoji" : "▶️"   },
{"id"   : 5 , "name": "$4"       , "class": "desc combine"               , "text" : "4"     , "visible" : true , "emoji" : ""   },
{"id"   : 6 , "name": "%5"       , "class": "desc "                      , "text" : "hotspot"     , "visible" : true , "emoji" : "🫕"   },
{"id"   : 7 , "name": "^6"       , "class": "desc "                      , "text" : "debug"     , "visible" : true , "emoji" : "🐞"   },
{"id"   : 8 , "name": ";7"       , "class": "desc "                      , "text" : "7"     , "visible" : true , "emoji" : ""   },
{"id"   : 9 , "name": "*8"       , "class": "desc "                      , "text" : "8"     , "visible" : true , "emoji" : ""   },
{"id"   : 10, "name": "(9"       , "class": "desc "                      , "text" : "9"     , "visible" : true , "emoji" : ""   },
{"id"   : 11, "name": ")0"       , "class": "desc "                      , "text" : "0"     , "visible" : true , "emoji" : ""   },
{"id"   : 12, "name": "_-"       , "class": "desc "                      , "text" : "-"     , "visible" : true , "emoji" : ""   },
{"id"   : 13, "name": "+="       , "class": "desc "                      , "text" : "="     , "visible" : true , "emoji" : ""   },
{"id"   : 14, "name": "delete"   , "class": "special r delete"           , "text" : "⌫"     , "visible" : true , "emoji" : ""   },  
{"id"   : 15, "name": "tab"      , "class": "special l tab"              , "text" : "chrome.refresh"   , "visible" : true , "emoji" : "🌐"   },
{"id"   : 16, "name": "Q"        , "class": "desc"                       , "text" : ""      , "visible" : true , "emoji" : "Q"  },
{"id"   : 17, "name": "W"        , "class": "desc"                       , "text" : ""      , "visible" : true , "emoji" : "W"  },
{"id"   : 18, "name": "E"        , "class": "desc "                      , "text" : ""      , "visible" : true , "emoji" : "E"  },
{"id"   : 19, "name": "R"        , "class": "desc"                       , "text" : ""      , "visible" : true , "emoji" : "R"  },
{"id"   : 20, "name": "T"        , "class": "desc"                       , "text" : ""      , "visible" : true , "emoji" : "T"  },
{"id"   : 21, "name": "Y"        , "class": ""                           , "text" : ""      , "visible" : true , "emoji" : "Y"  },
{"id"   : 22, "name": "U"        , "class": ""                           , "text" : ""      , "visible" : true , "emoji" : "U"  },
{"id"   : 23, "name": "I"        , "class": "desc"                       , "text" : ""      , "visible" : true , "emoji" : "I"  },
{"id"   : 24, "name": "O"        , "class": "desc"                       , "text" : ""      , "visible" : true , "emoji" : "O"  },
{"id"   : 25, "name": "P"        , "class": "desc"                       , "text" : ""      , "visible" : true , "emoji" : "P"  },
{"id"   : 26, "name": "{["       , "class": "desc"                       , "text" : "usage"     , "visible" : true , "emoji" : "👥"  },
{"id"   : 27, "name": "}]"       , "class": "desc"                       , "text" : "hierarchy"     , "visible" : true , "emoji" : "👶"  },
{"id"   : 28, "name": "|\\"      , "class": "desc"                       , "text" : "r2cursor"    , "visible" : true , "emoji" : "I"  },
{"id"   : 29, "name": "capslock" , "class": "special l caps-lock"        , "text" : "Caps"  , "visible" : true , "emoji" : ""   },
{"id"   : 30, "name": "A"        , "class": "desc"                       , "text" : ""      , "visible" : true , "emoji" : "A"  },
{"id"   : 31, "name": "S"        , "class": "desc "                      , "text" : ""      , "visible" : true , "emoji" : "S"  },
{"id"   : 32, "name": "D"        , "class": "desc "                      , "text" : ""      , "visible" : true , "emoji" : "D"  },
{"id"   : 33, "name": "F"        , "class": "desc "                      , "text" : ""      , "visible" : true , "emoji" : "F"  },
{"id"   : 34, "name": "G"        , "class": "desc"                       , "text" : ""      , "visible" : true , "emoji" : "G"  },
{"id"   : 35, "name": "H"        , "class": "desc "                      , "text" : ""      , "visible" : true , "emoji" : "H"  },
{"id"   : 36, "name": "J"        , "class": "desc "                      , "text" : ""      , "visible" : true , "emoji" : "J"  },
{"id"   : 37, "name": "K"        , "class": "desc "                      , "text" : ""      , "visible" : true , "emoji" : "K"  },
{"id"   : 38, "name": "L"        , "class": "desc "                      , "text" : ""      , "visible" : true , "emoji" : "L"  },
{"id"   : 39, "name": ":;"       , "class": "desc"                       , "text" : ";"     , "visible" : true , "emoji" : ":"  },
{"id"   : 40, "name": "\"'"      , "class": "desc"                       , "text" : "'"     , "visible" : true , "emoji" : "\"" },
{"id"   : 41, "name": "enter"    , "class": "special r enter"            , "text" : "return", "visible" : true , "emoji" : "⏎"  },
{"id"   : 42, "name": "lshift"   , "class": "special shift l"            , "text" : "shift" , "visible" : true , "emoji" : ""   },
{"id"   : 43, "name": "Z"        , "class": ""                           , "text" : ""      , "visible" : true , "emoji" : "Z"  },
{"id"   : 44, "name": "X"        , "class": ""                           , "text" : ""      , "visible" : true , "emoji" : "X"  },
{"id"   : 45, "name": "C"        , "class": ""                           , "text" : ""      , "visible" : true , "emoji" : "C"  },
{"id"   : 46, "name": "V"        , "class": ""                           , "text" : ""      , "visible" : true , "emoji" : "V"  },
{"id"   : 47, "name": "B"        , "class": ""                           , "text" : ""      , "visible" : true , "emoji" : "B"  },
{"id"   : 48, "name": "N"        , "class": ""                           , "text" : ""      , "visible" : true , "emoji" : "N"  },
{"id"   : 49, "name": "M"        , "class": ""                           , "text" : ""      , "visible" : true , "emoji" : "M"  },
{"id"   : 50, "name": "<,"       , "class": "desc"                       , "text" : ","     , "visible" : true , "emoji" : "<"  },
{"id"   : 51, "name": ">."       , "class": "desc"                       , "text" : "."     , "visible" : true , "emoji" : ">"  },
{"id"   : 52, "name": "?/"       , "class": "desc"                       , "text" : "/"     , "visible" : true , "emoji" : "?"  }, 
{"id"   : 53, "name": "rshift"   , "class": "special shift r"            , "text" : "shift" , "visible" : true , "emoji" : ""   },  
{"id"   : 54, "name": "lctrl"    , "class": "special tall less-padding l", "text" : "ctrl"  , "visible" : true , "emoji" : ""   },  
{"id"   : 55, "name": "win"      , "class": "special tall less-padding l", "text" : "win"   , "visible" : true , "emoji" : ""   },  
{"id"   : 56, "name": "lalt"     , "class": "special tall command r"     , "text" : "alt"   , "visible" : true , "emoji" : ""   },  
{"id"   : 57, "name": "space"    , "class": "special tall space"         , "text" : "evaluteExpression"      , "visible" : true , "emoji" : "🧮"   },
{"id"   : 58, "name": "ralt"     , "class": "special tall command l"     , "text" : "alt"   , "visible" : true , "emoji" : ""   },  
{"id"   : 59, "name": "fn"       , "class": "special tall less-padding r", "text" : "fn"    , "visible" : true , "emoji" : ""   },  
{"id"   : 60, "name": "↑"        , "class": "arrow up"                   , "text" : "↑"     , "visible" : true , "emoji" : ""   },  
{"id"   : 61, "name": "←"        , "class": "arrow"                      , "text" : "←"     , "visible" : true , "emoji" : ""   },  
{"id"   : 62, "name": "↓"        , "class": "arrow down"                 , "text" : "↓"     , "visible" : true , "emoji" : ""   },  
{"id"   : 63, "name": "→"        , "class": "arrow"                      , "text" : "→"     , "visible" : true , "emoji" : ""   },  
{"id"   : 64, "name": "fish_next", "class": "desc"                       , "text" : ""      , "visible" : false, "emoji" : ""   },
{"id"   : 65, "name": "fish_w"   , "class": "desc"                       , "text" : ""      , "visible" : false, "emoji" : ""   },
{"id"   : 66, "name": "fish_t"   , "class": "desc"                       , "text" : ""      , "visible" : false, "emoji" : ""   },
{"id"   : 67, "name": "home_next", "class": "desc"                       , "text" : ""      , "visible" : false, "emoji" : ""   },
{"id"   : 68, "name": "home_w"   , "class": "desc"                       , "text" : ""      , "visible" : false, "emoji" : ""   },
{"id"   : 69, "name": "home_t"   , "class": "desc"                       , "text" : ""      , "visible" : false, "emoji" : ""   },
{"id"   : 70, "name": "space_bak", "class": "desc enter"                 , "text" : ""      , "visible" : false, "emoji" : ""   },
{"id"   : 71, "name": "_bak"     , "class": "desc"                       , "text" : ""      , "visible" : false, "emoji" : ""   }
]